glmnet_classifier/__init__.py
glmnet_classifier/_version.py
glmnet_classifier/glmnet_classifier.py
glmnet_classifier/tests/__init__.py
glmnet_classifier/tests/test_common.py
glmnet_classifier/tests/test_glmnet_iris.py
glmnet_classifier/tests/test_glmnet_sparse.py
glmnet_python/GLMnet.so
glmnet_python/__init__.py
glmnet_python/coxnet.py
glmnet_python/cvcompute.py
glmnet_python/cvelnet.py
glmnet_python/cvfishnet.py
glmnet_python/cvglmnet.py
glmnet_python/cvglmnetCoef.py
glmnet_python/cvglmnetPlot.py
glmnet_python/cvglmnetPredict.py
glmnet_python/cvlognet.py
glmnet_python/cvmrelnet.py
glmnet_python/cvmultnet.py
glmnet_python/dataprocess.py
glmnet_python/elnet.py
glmnet_python/fishnet.py
glmnet_python/glmnet.py
glmnet_python/glmnetCoef.py
glmnet_python/glmnetControl.py
glmnet_python/glmnetPlot.py
glmnet_python/glmnetPredict.py
glmnet_python/glmnetPrint.py
glmnet_python/glmnetSet.py
glmnet_python/loadGlmLib.py
glmnet_python/lognet.py
glmnet_python/mrelnet.py
glmnet_python/printDict.py
glmnet_python/structtype.py
glmnet_python/wtmean.py
glmnet_classifier-0.1.44.dist-info/METADATA
glmnet_classifier-0.1.44.dist-info/WHEEL
glmnet_classifier-0.1.44.dist-info/top_level.txt
glmnet_classifier-0.1.44.dist-info/RECORD
