Metadata-Version: 2.1
Name: glmnet-classifier
Version: 0.1.44
Summary: A binomial classifier based on glmnet
Home-page: https://github.com/hrolfrc/glmnet-classifier
Download-URL: https://github.com/hrolfrc/glmnet-classifier
Maintainer: Carlson Research, LLC
Maintainer-email: hrolfrc@gmail.com
License: new BSD
Classifier: Intended Audience :: Science/Research
Classifier: Intended Audience :: Developers
Classifier: Development Status :: 2 - Pre-Alpha
Classifier: License :: OSI Approved
Classifier: Topic :: Scientific/Engineering
Classifier: Operating System :: Unix
Classifier: Programming Language :: Python :: 3
Requires-Dist: numpy
Requires-Dist: scipy
Requires-Dist: scikit-learn
Provides-Extra: docs
Requires-Dist: sphinx ; extra == 'docs'
Requires-Dist: sphinx-gallery ; extra == 'docs'
Requires-Dist: sphinx-rtd-theme ; extra == 'docs'
Requires-Dist: numpydoc ; extra == 'docs'
Requires-Dist: matplotlib ; extra == 'docs'
Provides-Extra: tests
Requires-Dist: pytest ; extra == 'tests'
Requires-Dist: pytest-cov ; extra == 'tests'
